{
  "name": "@fullstackjosh/web-components",
  "entries": [
    {
      "version": "0.1.0",
      "tag": "@fullstackjosh/web-components_v0.1.0",
      "date": "Mon, 30 Oct 2023 08:11:10 GMT",
      "comments": {
        "none": [
          {
            "comment": "move dependency on rimraf to vite.config"
          },
          {
            "comment": "docs: add installation command to readme"
          }
        ],
        "minor": [
          {
            "comment": "chore: limit files published to NPM"
          },
          {
            "comment": "feat: FoldableTextArea"
          },
          {
            "comment": "fix: use correct es vs cjs filenames in build output"
          }
        ],
        "dependency": [
          {
            "comment": "Updating dependency \"rollup-plugin-content-chunks\" from `0.0.1` to `0.1.0`"
          }
        ]
      }
    },
    {
      "version": "0.0.4",
      "tag": "@fullstackjosh/web-components_v0.0.4",
      "date": "Sat, 09 Sep 2023 11:11:20 GMT",
      "comments": {
        "patch": [
          {
            "comment": "feat: use innerHTML to set panel title and content"
          }
        ]
      }
    },
    {
      "version": "0.0.3",
      "tag": "@fullstackjosh/web-components_v0.0.3",
      "date": "Sat, 09 Sep 2023 08:02:59 GMT",
      "comments": {
        "patch": [
          {
            "comment": "fix: did not build before publishing"
          }
        ]
      }
    },
    {
      "version": "0.0.2",
      "tag": "@fullstackjosh/web-components_v0.0.2",
      "date": "Sat, 09 Sep 2023 07:54:13 GMT",
      "comments": {
        "patch": [
          {
            "comment": "fix: split out Handlebars dependency"
          }
        ]
      }
    },
    {
      "version": "0.0.1",
      "tag": "@fullstackjosh/web-components_v0.0.1",
      "date": "Sat, 09 Sep 2023 05:59:19 GMT",
      "comments": {
        "patch": [
          {
            "comment": "feat: foldable panel (initial release)"
          }
        ]
      }
    }
  ]
}
